[{"id":29,"closed":false,"offers_count":1,"user_id":1,"created_at":"2020-06-16T22:23:10.695Z","updated_at":"2020-06-16T22:23:10.695Z","title":"23112","description":null,"system_id":30,"system":{"id":30,"latitude":"31.23266","longitude":"29.944364","consumption":2313,"backup":false,"address":"28 Street 5, Mustafa Kamel WA Bolkli, Sidi Gaber, Alexandria Governorate, Egypt","city":"Alexandria","country":"Egypt","user_id":1,"created_at":"2020-06-16T22:22:58.795Z","updated_at":"2020-06-16T22:22:58.795Z","cost":"1096375.5","calculation":{"id":30,"system_circuits":14,"panels_num":86,"panel_watt":250,"battery_Ah":200,"batteries_num":72,"inverter_watt":2200,"mppt_amp":80,"system_id":30,"created_at":"2020-06-16T22:22:58.837Z","updated_at":"2020-06-16T22:22:58.837Z"}},"user":{"id":1,"provider":"email","uid":"ahmed@mail.com","allow_password_change":false,"name":"ahmed","image":null,"email":"ahmed@mail.com","created_at":"2020-06-16T20:07:38.167Z","updated_at":"2020-06-16T22:35:20.157Z","username":"ahmed"}},{"id":22,"closed":false,"offers_count":5,"user_id":1,"created_at":"2020-06-16T20:07:52.515Z","updated_at":"2020-06-16T20:07:52.515Z","title":"Renee Sance","description":"Ullam earum asperiores. Deleniti necessitatibus rerum. Eligendi et ab. Enim error ex. Et consequuntur esse. Accusantium quos sed. Quia et aliquid. Hic perspiciatis eveniet. Et sint tempore. Ut ratione veritatis. Alias s.","system_id":22,"system":{"id":22,"latitude":"-48.715493","longitude":"35.773773","consumption":179,"backup":true,"address":"Suite 173 4032 Kilback Lodge, North Vanda, KS 55302","city":"Lake Mia","country":"Virgin Islands, U.S.","user_id":1,"created_at":"2020-06-16T20:07:52.424Z","updated_at":"2020-06-16T20:07:52.424Z","cost":"30937.5","calculation":{"id":22,"system_circuits":3,"panels_num":24,"panel_watt":250,"battery_Ah":200,"batteries_num":28,"inverter_watt":1607,"mppt_amp":55,"system_id":22,"created_at":"2020-06-16T20:07:52.460Z","updated_at":"2020-06-16T20:07:52.460Z"}},"user":{"id":1,"provider":"email","uid":"ahmed@mail.com","allow_password_change":false,"name":"ahmed","image":null,"email":"ahmed@mail.com","created_at":"2020-06-16T20:07:38.167Z","updated_at":"2020-06-16T22:35:20.157Z","username":"ahmed"}},{"id":13,"closed":false,"offers_count":0,"user_id":1,"created_at":"2020-06-16T20:07:51.160Z","updated_at":"2020-06-16T20:07:51.160Z","title":"Walt Smedley","description":"Occaecati voluptate et. Labore nihil delectus. Excepturi qui consectetur. Sit aut natus. Quas vero at. Explicabo quis voluptas. Deleniti porro iusto. Dolores explicabo voluptas. Dolorum alias quos. Necessitatibus nihil .","system_id":13,"system":{"id":13,"latitude":"-10.050651","longitude":"85.072092","consumption":206,"backup":false,"address":"971 Wesley Ports, Strackechester, KS 38789-8025","city":"Port Shayneshire","country":"Tonga","user_id":1,"created_at":"2020-06-16T20:07:51.071Z","updated_at":"2020-06-16T20:07:51.071Z","cost":"31779.0","calculation":{"id":13,"system_circuits":5,"panels_num":13,"panel_watt":250,"battery_Ah":200,"batteries_num":2,"inverter_watt":1190,"mppt_amp":78,"system_id":13,"created_at":"2020-06-16T20:07:51.106Z","updated_at":"2020-06-16T20:07:51.106Z"}},"user":{"id":1,"provider":"email","uid":"ahmed@mail.com","allow_password_change":false,"name":"ahmed","image":null,"email":"ahmed@mail.com","created_at":"2020-06-16T20:07:38.167Z","updated_at":"2020-06-16T22:35:20.157Z","username":"ahmed"}}]